Workbook

Sheet Dashboard
A1: Queuing Solutions – Engineering Progress Dashboard
A3: Overall Weighted % Complete: | B3: =AVERAGE('Module Audit'!F2:F77)
A5: Status | B5: Count | C5: % of Total
A6: Fully Working | B6: =COUNTIF('Module Audit'!E2:E77,"Fully Working") | C6: =B6/76
A7: Partially Working | B7: =COUNTIF('Module Audit'!E2:E77,"Partially Working") | C7: =B7/76
A8: Scaffolded | B8: =COUNTIF('Module Audit'!E2:E77,"Scaffolded") | C8: =B8/76
A9: Broken | B9: =COUNTIF('Module Audit'!E2:E77,"Broken") | C9: =B9/76
A10: Not Started | B10: =COUNTIF('Module Audit'!E2:E77,"Not Started") | C10: =B10/76
A13: Module Group | B13: % Complete (weighted) | C13: Count
A14: M0 – Platform Foundation | B14: =AVERAGEIF('Module Audit'!C2:C77,A14,'Module Audit'!F2:F77) | C14: =COUNTIF('Module Audit'!C2:C77,A14)
A15: M1 – Company Onboarding | B15: =AVERAGEIF('Module Audit'!C2:C77,A15,'Module Audit'!F2:F77) | C15: =COUNTIF('Module Audit'!C2:C77,A15)
A16: M10 – Super Admin Console | B16: =AVERAGEIF('Module Audit'!C2:C77,A16,'Module Audit'!F2:F77) | C16: =COUNTIF('Module Audit'!C2:C77,A16)
A17: M11 – Frontend / Public Pages | B17: =AVERAGEIF('Module Audit'!C2:C77,A17,'Module Audit'!F2:F77) | C17: =COUNTIF('Module Audit'!C2:C77,A17)
A18: M2 – Branch & Staff Management | B18: =AVERAGEIF('Module Audit'!C2:C77,A18,'Module Audit'!F2:F77) | C18: =COUNTIF('Module Audit'!C2:C77,A18)
A19: M3 – Queue Method 1 | B19: =AVERAGEIF('Module Audit'!C2:C77,A19,'Module Audit'!F2:F77) | C19: =COUNTIF('Module Audit'!C2:C77,A19)
A20: M4 – Queue Method 2 | B20: =AVERAGEIF('Module Audit'!C2:C77,A20,'Module Audit'!F2:F77) | C20: =COUNTIF('Module Audit'!C2:C77,A20)
A21: M5 – Queue Method 3 | B21: =AVERAGEIF('Module Audit'!C2:C77,A21,'Module Audit'!F2:F77) | C21: =COUNTIF('Module Audit'!C2:C77,A21)
A22: M6 – Queue Method 4 | B22: =AVERAGEIF('Module Audit'!C2:C77,A22,'Module Audit'!F2:F77) | C22: =COUNTIF('Module Audit'!C2:C77,A22)
A23: M7 – KOT Kiosk | B23: =AVERAGEIF('Module Audit'!C2:C77,A23,'Module Audit'!F2:F77) | C23: =COUNTIF('Module Audit'!C2:C77,A23)
A24: M8 – Notifications & Alerts | B24: =AVERAGEIF('Module Audit'!C2:C77,A24,'Module Audit'!F2:F77) | C24: =COUNTIF('Module Audit'!C2:C77,A24)
A25: M9 – Analytics & Reporting | B25: =AVERAGEIF('Module Audit'!C2:C77,A25,'Module Audit'!F2:F77) | C25: =COUNTIF('Module Audit'!C2:C77,A25)
A28: Priority | B28: % Complete (weighted) | C28: Count
A29: Must | B29: =AVERAGEIF('Module Audit'!D2:D77,A29,'Module Audit'!F2:F77) | C29: =COUNTIF('Module Audit'!D2:D77,A29)
A30: Should | B30: =AVERAGEIF('Module Audit'!D2:D77,A30,'Module Audit'!F2:F77) | C30: =COUNTIF('Module Audit'!D2:D77,A30)
A31: Could | B31: =AVERAGEIF('Module Audit'!D2:D77,A31,'Module Audit'!F2:F77) | C31: =COUNTIF('Module Audit'!D2:D77,A31)
A34: Top Blockers – Must-Priority Items (Worst Shape First)
A35: ID | B35: Feature | C35: Status | D35: Blocker
A36: M11-04 | B36: Password Reset / Forgot Password | C36: Scaffolded | D36: No backend reset endpoint; no token-based reset flow; email backend is console anyway
A37: M1-04 | B37: Stripe Checkout / Payment Integration | C37: Partially Working | D37: STRIPE_SECRET_KEY not in .env; StripeSimulatorView exists as sandbox fallback
A38: M5-01 | B38: Full-Screen Live Display Board (Now Serving) | C38: Partially Working | D38: display/views.py is empty (4 lines, no implementation). PublicDisplayView is in queuing/views.py but display app has no routes registered
A39: M5-02 | B39: Real-time Token Flip (WebSocket on display board) | C39: Partially Working | D39: Cannot confirm WS connection succeeds without runtime test
A40: M8-03 | B40: Automated Alert Checks (Celery periodic tasks) | C40: Partially Working | D40: Celery broker defaults to memory:// – tasks not durable; no Celery worker running in dev setup

Sheet Module Audit
A1: ID | B1: Feature | C1: Module Group | D1: Priority | E1: Status | F1: % Complete | G1: Backend Evidence | H1: Frontend Evidence | I1: End-to-End Wired? | J1: Tested? | K1: Confidence | L1: Blockers | M1: Next Step to Close Gap
A2: M0-01 | B2: Django Project Setup & ASGI Config | C2: M0 – Platform Foundation | D2: Must | E2: Fully Working | F2: 100 | G2: backend/queuing_solutions/settings.py; asgi.py | H2: N/A | I2: Y | J2: Y – test_phase1.py | K2: High | L2: None | M2: —
A3: M0-02 | B3: MySQL/MariaDB Database & Migrations | C3: M0 – Platform Foundation | D3: Must | E3: Fully Working | F3: 100 | G3: backend/queuing_solutions/settings.py; 9 migration dirs | H3: N/A | I3: Y | J3: Y – test_models.py | K3: High | L3: MariaDB version-check monkey-patched (settings.py:17) | M3: Upgrade XAMPP/MariaDB to ≥10.5 to remove monkey-patch
A4: M0-03 | B4: JWT Authentication (Login / Logout / Refresh) | C4: M0 – Platform Foundation | D4: Must | E4: Fully Working | F4: 100 | G4: accounts/views.py – CustomTokenObtainPairView, LogoutView; /api/auth/login|logout|refresh | H4: src/routes/login.tsx; src/lib/quesole/store.tsx:signIn() | I4: Y | J4: Y – test_auth.py (5 tests pass) | K4: High | L4: None | M4: —
A5: M0-04 | B5: Role-Based Access Control (RBAC) | C5: M0 – Platform Foundation | D5: Must | E5: Fully Working | F5: 100 | G5: core/permissions.py – IsSuperAdmin, IsCompanyAdmin, IsBranchAdmin, IsDeskStaff | H5: src/routes/app.tsx – role-gated nav; src/lib/quesole/store.tsx | I5: Y | J5: Y – test_rbac.py (passes) | K5: High | L5: None | M5: —
A6: M0-05 | B6: Multi-Tenant Isolation (company-scoped querysets) | C6: M0 – Platform Foundation | D6: Must | E6: Fully Working | F6: 100 | G6: core/managers.py – TenantManager applied to all models | H6: store.tsx filters by session.companyId | I6: Y | J6: Y – test_tenant_isolation.py (3 pass) | K6: High | L6: None | M6: —
A7: M0-06 | B7: WebSocket / Django Channels (Real-time) | C7: M0 – Platform Foundation | D7: Must | E7: Fully Working | F7: 100 | G7: core/consumers.py – QueueConsumer; queuing/views.py:broadcast_queue_update() | H7: store.tsx:593 – ws://hostname:8000/ws/branch/… | I7: Y | J7: Y – test_websocket.py; test_phase2.py::test_websocket_pii_segregation | K7: High | L7: InMemoryChannelLayer used (no Redis configured) – not suitable for multi-process prod | M7: Set REDIS_URL env var to switch to RedisChannelLayer
A8: M0-07 | B8: Health-check endpoint | C8: M0 – Platform Foundation | D8: Should | E8: Fully Working | F8: 100 | G8: core/views.py:healthz; /healthz | H8: N/A | I8: Y | J8: N | K8: High | L8: None | M8: Add a smoke test
A9: M0-08 | B9: Audit Log (AuditLog model + write) | C9: M0 – Platform Foundation | D9: Should | E9: Fully Working | F9: 100 | G9: audit/models.py; audit/utils.py:log_audit(); /api/audit-logs/ | H9: super-admin.tsx renders audit log tab | I9: Y | J9: N – unit tests not found for audit | K9: Medium | L9: No dedicated audit tests | M9: Add test_audit.py
A10: M0-09 | B10: API Schema / Swagger Docs | C10: M0 – Platform Foundation | D10: Could | E10: Fully Working | F10: 100 | G10: drf_spectacular; /api/schema/ /api/docs/ /api/redoc/ | H10: N/A | I10: Y | J10: N | K10: High | L10: None | M10: —
A11: M0-10 | B11: Prometheus Metrics | C11: M0 – Platform Foundation | D11: Could | E11: Fully Working | F11: 100 | G11: django_prometheus middleware; /metrics route | H11: N/A | I11: Y | J11: N | K11: Unverified | L11: Not verified at runtime | M11: Hit /metrics and confirm output
A12: M1-01 | B12: Company Registration (multi-step wizard) | C12: M1 – Company Onboarding | D12: Must | E12: Fully Working | F12: 100 | G12: companies/views.py:CompanyRegistrationView; POST /api/companies/register/ | H12: src/routes/signup.tsx (multi-step wizard, 42 KB) | I12: Y | J12: Y – test_phase1.py | K12: High | L12: CAPTCHA is MOCK_CAPTCHA_TOKEN on frontend ($companySlug.tsx:187) | M12: Integrate real reCAPTCHA or hCaptcha
A13: M1-02 | B13: Subscription Package Selection (Starter/Standard/Advanced/Enterprise) | C13: M1 – Company Onboarding | D13: Must | E13: Fully Working | F13: 100 | G13: billing/models.py:Package; /api/packages/ | H13: src/routes/signup.tsx – plan selection step; src/routes/pricing.tsx | I13: Y | J13: Y – test_entitlements.py | K13: High | L13: None | M13: —
... A77: M11-10 | B77: Data Backup & Retention (PII purge + DB backup) | C77: M11 – Frontend / Public Pages | D77: Could | E77: Partially Working | F77: 50 | G77: core/backup.py:run_mysql_backup(); core/tasks.py:purge_expired_customer_pii(); Celery beat schedules both | H77: N/A | I77: N | J77: Y – test_phase7.py covers PII purge logic | K77: Unverified | L77: Celery must be running; DB backup uses mysqldump which must be on PATH | M77: Run Celery beat; verify mysqldump available; test backup file creation

Sheet Untracked - Extra Code
A1: Path / Location | B1: Description
A2: src/components/site/scroll-controlled-background.tsx | B2: Scroll-linked background video (MOD-01 from completed_modules.xlsx) – frontend-only visual enhancement, not in main spec
A3: completed_modules.xlsx | B3: Separate UI polish module tracker (MOD-01…MOD-10) tracking frontend visual improvements – not in main breakdown sheet
A4: backend/tests/locustfile.py | B4: Locust load-testing script (~200 lines) – not listed in spec but useful
A5: backend/tests/test_scenario57.py | B5: Specific scenario test file named 'scenario57' – purpose unclear from name alone
A6: backend/billing/stripe_helper.py | B6: Stripe helper module (3 KB) wrapping stripe API – not explicitly in breakdown as separate module
A7: backend/core/honeypot.py | B7: Bot honeypot field validator – security extra beyond spec
A8: backend/core/throttles.py | B8: Custom DRF throttle classes – beyond baseline spec
A9: backend/core/crypto.py | B9: Custom blind-index + tracking-code generator – beyond spec, supports PII encryption
A10: backend/subscriptions/ | B10: Empty subscriptions/ app directory – stubs with only a services/ subdir; functionality is in billing/ instead
A11: backend/qrcodes/ | B11: qrcodes/ directory contains only SVG files (static assets) – not an app module
A12: backend/backups/ | B12: backups/ directory – runtime backup output location (not a Django app)
... A16: src/lib/quesole/store.tsx:1601 | B16: store.tsx line 1601 comment: 'Calculated mock/live trend percentages vs. yesterday/last hour' – dashboard delta percentages are computed locally, not from backend
